persistpg/__init__.py
persistpg/client.py
persistpg/connection.py
persistpg/commands/__init__.py
persistpg/commands/cleanup.py
persistpg/commands/decr.py
persistpg/commands/delete.py
persistpg/commands/exists.py
persistpg/commands/expire.py
persistpg/commands/find.py
persistpg/commands/flushall.py
persistpg/commands/get.py
persistpg/commands/incr.py
persistpg/commands/lock.py
persistpg/commands/mget.py
persistpg/commands/mset.py
persistpg/commands/namespace.py
persistpg/commands/persist.py
persistpg/commands/rate_limit.py
persistpg/commands/scan.py
persistpg/commands/search.py
persistpg/commands/set.py
persistpg/commands/setnx.py
persistpg/commands/ttl.py
persistpg/commands/unique.py
persistpg/utils/__init__.py
persistpg/utils/patterns.py
persistpg/utils/serialization.py
persistpg-0.1.3.dist-info/METADATA
persistpg-0.1.3.dist-info/WHEEL
persistpg-0.1.3.dist-info/top_level.txt
persistpg-0.1.3.dist-info/RECORD
