Metadata-Version: 2.1
Name: persistpg
Version: 0.1.3
Summary: A fast, Redis-like key/value store built on PostgreSQL and asyncpg.
Home-page: UNKNOWN
License: MIT
Keywords: postgresql,redis,key-value,jsonb,asyncio,asyncpg
Platform: UNKNOWN
Classifier: Development Status :: 4 - Beta
Classifier: Intended Audience :: Developers
Classifier: License :: OSI Approved :: MIT License
Classifier: Programming Language :: Python :: 3
Classifier: Programming Language :: Python :: 3 :: Only
Classifier: Programming Language :: Python :: 3.10
Classifier: Programming Language :: Python :: 3.11
Classifier: Programming Language :: Python :: 3.12
Classifier: Topic :: Database
Classifier: Topic :: Software Development :: Libraries
Requires-Python: >=3.10
Requires-Dist: asyncpg<0.30,>=0.29
Provides-Extra: orjson
Requires-Dist: orjson>=3.10; extra == "orjson"
